uapg/__init__.py
uapg/cli.py
uapg/db_manager.py
uapg/event_filter.py
uapg/history_pgsql.py
uapg/history_timescale.py
uapg/py.typed
uapg/test_event_filter.py
uapg-0.1.13.dist-info/licenses/LICENSE
uapg-0.1.13.dist-info/METADATA
uapg-0.1.13.dist-info/WHEEL
uapg-0.1.13.dist-info/top_level.txt
uapg-0.1.13.dist-info/RECORD
