Metadata-Version: 2.4
Name: uapg
Version: 0.1.13
Summary: OPC UA PostgreSQL History Storage Backend
Author-email: CyberNet-Git <v.v.panfilov@gmail.com>
License-Expression: MIT
Project-URL: Homepage, https://github.com/CyberNet-Git/uapg
Project-URL: Repository, https://github.com/CyberNet-Git/uapg
Project-URL: Documentation, https://github.com/CyberNet-Git/uapg#readme
Project-URL: Issues, https://github.com/CyberNet-Git/uapg/issues
Keywords: opc-ua,postgresql,timescaledb,history,industrial
Classifier: Development Status :: 4 - Beta
Classifier: Intended Audience :: Developers
Classifier: Programming Language :: Python :: 3
Classifier: Programming Language :: Python :: 3.12
Classifier: Topic :: Database
Classifier: Topic :: Scientific/Engineering :: Information Analysis
Requires-Python: >=3.12
License-File: LICENSE
Requires-Dist: asyncua>=1.0.0
Requires-Dist: asyncpg>=0.29.0
Provides-Extra: dev
Requires-Dist: pytest>=7.0.0; extra == "dev"
Requires-Dist: pytest-asyncio>=0.21.0; extra == "dev"
Requires-Dist: black>=23.0.0; extra == "dev"
Requires-Dist: isort>=5.12.0; extra == "dev"
Requires-Dist: mypy>=1.0.0; extra == "dev"
Dynamic: license-file
